<?xml version="1.0" encoding="utf-8"?>
<!DOCTYPE beans PUBLIC "-//SPRING//DTD BEAN//EN" "http://www.springframework.org/dtd/spring-beans.dtd">

<beans>

  <!-- Pre-defined boolean values for convenience:  -->
  <bean id="VALUE_TRUE" class="org.vortikal.repository.resourcetype.Value">
    <constructor-arg type="boolean">
      <value>true</value>
    </constructor-arg>
  </bean>

  <bean id="VALUE_FALSE" class="org.vortikal.repository.resourcetype.Value">
    <constructor-arg type="boolean">
      <value>false</value>
    </constructor-arg>
  </bean>

  <!-- Value factory -->
  <bean id="valueFactory" class="org.vortikal.repository.resourcetype.ValueFactoryImpl">
    <property name="principalFactory" ref="principalFactory" />
  </bean>


  <bean id="abstractPropDef" abstract="true">
    <property name="valueFactory" ref="valueFactory"/>
    <property name="valueFormatterRegistry" ref="valueFormatterRegistry" />
  </bean>
  
</beans>
